mellow_sdk/__init__.py
mellow_sdk/backtest.py
mellow_sdk/data.py
mellow_sdk/history.py
mellow_sdk/portfolio.py
mellow_sdk/positions.py
mellow_sdk/primitives.py
mellow_sdk/strategies.py
mellow_sdk/uniswap_utils.py
mellow_sdk/utils.py
mellow_sdk/viewers.py
mellow_strategy_sdk-0.1.1.dist-info/LICENSE
mellow_strategy_sdk-0.1.1.dist-info/WHEEL
mellow_strategy_sdk-0.1.1.dist-info/METADATA
mellow_strategy_sdk-0.1.1.dist-info/RECORD
