Metadata-Version: 2.1
Name: mellow-strategy-sdk
Version: 0.1.1
Summary: Framework for creating new Uniswap V3 strategies
Home-page: https://mellow.finance/
License: MIT
Author: Alex K
Author-email: ak@mellow.finance
Requires-Python: >=3.7.13,<4.0.0
Classifier: License :: OSI Approved :: MIT License
Classifier: Programming Language :: Python :: 3
Classifier: Programming Language :: Python :: 3.10
Classifier: Programming Language :: Python :: 3.8
Classifier: Programming Language :: Python :: 3.9
Provides-Extra: docs
Requires-Dist: PyYAML (>=3.13,<4.0)
Requires-Dist: arviz (>=0.12.0,<0.13.0)
Requires-Dist: autodoc (>=0.5.0,<0.6.0); extra == "docs"
Requires-Dist: boto3 (>=1.0.0,<2.0.0)
Requires-Dist: folium (==0.2.1)
Requires-Dist: kaleido (==0.2.1)
Requires-Dist: myst-parser (>=0.17.0,<0.18.0); extra == "docs"
Requires-Dist: pandas (>=1.3.5,<1.4.0)
Requires-Dist: plotly (>=5.5.0,<6.0.0)
Requires-Dist: polars (==0.13.17)
Requires-Dist: pyarrow (>=6.0.1,<7.0.0)
Requires-Dist: python-binance (>=1.0.15,<2.0.0)
Requires-Dist: six (>=1.15.0,<1.16.0)
Requires-Dist: sphinx (>=4,<5); extra == "docs"
Requires-Dist: sphinx-autodoc-typehints (>=1.17.0,<2.0.0); extra == "docs"
Requires-Dist: sphinx-autodocgen (>=1.3,<2.0); extra == "docs"
Requires-Dist: sphinx-rtd-theme (>=1.0.0,<2.0.0); extra == "docs"
Requires-Dist: sphinxcontrib-napoleon (>=0.7,<0.8); extra == "docs"
Requires-Dist: structlog (>=21.5.0,<22.0.0)
Project-URL: Documentation, https://mellow-strategy-sdk.readthedocs.io/en/main/
Project-URL: Repository, https://github.com/mellow-finance/mellow-strategy-sdk
